ghostos_moss-0.3.7.dist-info/METADATA
ghostos_moss-0.3.7.dist-info/WHEEL
ghostos_moss-0.3.7.dist-info/entry_points.txt
ghostos_moss-0.3.7.dist-info/licenses/LICENSE
ghostos_moss/__init__.py
ghostos_moss/abcd.py
ghostos_moss/examples/baseline.py
ghostos_moss/examples/funcs_with_typing.py
ghostos_moss/examples/has_exports.py
ghostos_moss/examples/random_moss.py
ghostos_moss/examples/self_update_moss.py
ghostos_moss/examples/suite_example.py
ghostos_moss/examples/with_exports.py
ghostos_moss/exports.py
ghostos_moss/lifecycle.py
ghostos_moss/magics.py
ghostos_moss/modules.py
ghostos_moss/moss_impl.py
ghostos_moss/prompts.py
ghostos_moss/pycontext.py
ghostos_moss/self_updater.py
ghostos_moss/testsuite.py
ghostos_moss/utils.py
ghostos_moss-0.3.7.dist-info/RECORD
