Metadata-Version: 2.1
Name: ghostos-moss
Version: 0.3.7
Summary: the code-driven python interface for llms, agents and project GhostOS
Author-Email: thirdgerb <thirdgerb@gmail.com>
License: MIT
Requires-Python: >=3.10
Requires-Dist: ghostos-common>=0.3.3
Requires-Dist: ghostos-container>=0.2.4
